netdots/__init__.py
netdots/api_client.py
netdots/integrations/__init__.py
netdots/integrations/integrations.py
netdots/integrations/jira.py
netdots/integrations/skype.py
netdots-0.1.14.dist-info/METADATA
netdots-0.1.14.dist-info/WHEEL
netdots-0.1.14.dist-info/top_level.txt
netdots-0.1.14.dist-info/RECORD
