Metadata-Version: 2.4
Name: netdots
Version: 0.1.14
Summary: Netdots Library - A Python SDK for interacting with the Netdots API.
Home-page: https://netdots.com
Author: Netdots
Author-email: support@netdots.com
Classifier: Programming Language :: Python :: 3
Classifier: Operating System :: OS Independent
Requires-Python: >=3.7
Requires-Dist: requests
Dynamic: author
Dynamic: author-email
Dynamic: classifier
Dynamic: description
Dynamic: description-content-type
Dynamic: home-page
Dynamic: requires-dist
Dynamic: requires-python
Dynamic: summary
